{
  "games": [
    {
      "gameNumber": 1713,
      "word": "LANCE",
      "date": "2/26/2026",
      "hints": {
        "synonym": "spear",
        "haiku": "The knight lowers point / Across the field they will meet / Steel decides the day"
      }
    },
    {
      "gameNumber": 1714,
      "word": "DIZZY",
      "date": "2/27/2026",
      "hints": {
        "synonym": "lightheaded",
        "haiku": "The room starts to spin / Ground uncertain beneath feet / Balance abandons"
      }
    }
  ],
  "recentUsedWords": [
    "CHIDE",
    "SWOOP",
    "GAVEL",
    "BLEAT",
    "EMBED",
    "CELLO",
    "SCENE",
    "VEGAN",
    "SURGE",
    "MOOCH",
    "BLOOM",
    "SKULL",
    "ROOST",
    "SQUAD",
    "MOGUL",
    "HOIST",
    "STANK",
    "AWAKE",
    "GUAVA",
    "ATTIC",
    "BUYER",
    "SHRED",
    "LANCE",
    "DIZZY"
  ]
}